forestmq/__init__.py
forestmq/consumer.py
forestmq/exceptions.py
forestmq/logger.py
forestmq/provider.py
forestmq/session.py
forestmq-0.2.1.dist-info/licenses/LICENSE
forestmq-0.2.1.dist-info/METADATA
forestmq-0.2.1.dist-info/WHEEL
forestmq-0.2.1.dist-info/top_level.txt
forestmq-0.2.1.dist-info/RECORD
